pyeztrace/__init__.py
pyeztrace/cli.py
pyeztrace/config.py
pyeztrace/custom_logging.py
pyeztrace/exceptions.py
pyeztrace/otel.py
pyeztrace/printing.py
pyeztrace/setup.py
pyeztrace/tracer.py
pyeztrace/viewer.py
pyeztrace-0.0.14.dist-info/licenses/LICENSE
pyeztrace-0.0.14.dist-info/METADATA
pyeztrace-0.0.14.dist-info/WHEEL
pyeztrace-0.0.14.dist-info/entry_points.txt
pyeztrace-0.0.14.dist-info/top_level.txt
pyeztrace-0.0.14.dist-info/RECORD
