Metadata-Version: 2.4
Name: pyeztrace
Version: 0.0.14
Summary: A dependency-free, lightweight Python tracing and logging library
Author: Jefferson Nelsson
Author-email: Jefferson Nelsson <jefferson.nelsson@gmail.com>
License: MIT
Keywords: logging,tracing,monitoring,debugging,performance
Classifier: Programming Language :: Python
Classifier: Programming Language :: Python :: 3
Classifier: Programming Language :: Python :: 3.7
Classifier: Programming Language :: Python :: 3.8
Classifier: Programming Language :: Python :: 3.9
Classifier: Programming Language :: Python :: 3.10
Classifier: Programming Language :: Python :: 3.11
Classifier: Programming Language :: Python :: 3.12
Classifier: Programming Language :: Python :: 3.13
Classifier: Programming Language :: Python :: Implementation :: CPython
Classifier: Operating System :: OS Independent
Requires-Python: >=3.7
License-File: LICENSE
Provides-Extra: otel
Requires-Dist: opentelemetry-api>=1.23.0; extra == "otel"
Requires-Dist: opentelemetry-sdk>=1.23.0; extra == "otel"
Requires-Dist: opentelemetry-exporter-otlp>=1.23.0; extra == "otel"
Provides-Extra: s3
Requires-Dist: boto3>=1.28.0; extra == "s3"
Provides-Extra: azure
Requires-Dist: azure-storage-blob>=12.14.0; extra == "azure"
Provides-Extra: all
Requires-Dist: pyeztrace[azure,otel,s3]; extra == "all"
Dynamic: author
Dynamic: license-file
Dynamic: requires-python
